JsonWalker/_version.py
JsonWalker/walk.py
JsonWalker/Legacy/walk.py
JsonWalker/Legacy/PathItems/AddContext.py
JsonWalker/Legacy/PathItems/Constants.py
JsonWalker/Legacy/PathItems/Default.py
JsonWalker/Legacy/PathItems/DictIter.py
JsonWalker/Legacy/PathItems/Index.py
JsonWalker/Legacy/PathItems/Key.py
JsonWalker/Legacy/PathItems/MultiValue.py
JsonWalker/Legacy/PathItems/PathDivider.py
JsonWalker/Legacy/PathItems/PathItem.py
jsonwalker-1.2.1.dist-info/METADATA
jsonwalker-1.2.1.dist-info/WHEEL
jsonwalker-1.2.1.dist-info/top_level.txt
jsonwalker-1.2.1.dist-info/RECORD
