Metadata-Version: 2.4
Name: JsonWalker
Version: 1.2.1
Summary: This is a easy to use library for walking through json data.
Home-page: https://github.com/byuawsfhtl/JsonWalker.git
Author: Record Linking Lab
Author-email: recordlinkinglab@gmail.com
Project-URL: Bug Tracker, https://github.com/byuawsfhtl/JsonWalker/issues
Dynamic: author
Dynamic: author-email
Dynamic: description
Dynamic: description-content-type
Dynamic: home-page
Dynamic: project-url
Dynamic: summary
